Workbook

Sheet Summary
K1: HOSPITAL MEDICAL SUMMARY REPORT
L6: Report Date | N6: =TODAY() -> 46027
A11: Patient Summary | G11: Billing Summary
A14: Total Patients | C14: =COUNTA('Patients Record '!A5:A24) -> 20 | G14: Total Billing Amount | I14: =SUM(' OPD Billing '!G5:G14) -> 50000
A16: New Patients (This Month) | C16: =COUNTIFS('Patients Record '!F5:F24,">="&EOMONTH(TODAY(),-1)+1,'Patients Record '!F5:F24,"<="&TODAY()) -> 0
G17: Paid Amount | I17: =SUMIF(' OPD Billing '!H5:H14,"Paid",' OPD Billing '!G5:G14) -> 50000
G20: Unpaid Amount | I20: =SUMIF(' OPD Billing '!H5:H14,"Unpaid",' OPD Billing '!G5:G14) -> 0
A23: Visit Summary | G23: Total Unpaid Bills | I23: =COUNTIF(' OPD Billing '!H5:H14,"Unpaid") -> 0
A26: Total Visits | C26: =COUNTA(#REF!) -> 1
A28: Todays Visits | C28: =COUNTIF(#REF!,TODAY()) -> #REF!
A31: This month visits | C31: =COUNTIFS(#REF!,">="&EOMONTH(TODAY(),-1)+1,#REF!,"<="&TODAY()) -> #REF!

Sheet Patients Record 
C1: Patients Record
A4: Patient ID | B4: Name | C4: DOB | D4: Age | E4: Gender | F4: Registration Date | G4: Mobile No. | H4: Alternate Mobile No. | I4: Address | J4: Blood Group | K4: Insurance | L4: Current Condition | M4: Condition Transition | N4: Status | O4: Total Amount | P4: Payment status
A5: P-001 | B5: Name 1 | C5: 20387 | D5: =IF(C5="","",DATEDIF(C5,TODAY(),"Y")) -> 70 | E5: Male | F5: 45358 | G5: xxx-xxxxxxx | H5: xxx-xxxxxxx | I5: xyz | J5: A+ | K5: Yes | L5: =IF(_xlfn.XLOOKUP(Tbl.PatRec[[#This Row],[Patient ID]],tblIPD[Patient id.],tblIPD[Patient id.],"")<>"","Admitted (IPD)",IF(_xlfn.XLOOKUP(Tbl.PatRec[[#This Row],[Patient ID]],tblOPD[Patient id.],tblOPD[Patient id.],"")<>"","Active OPD","Registered")) -> Admitted (IPD) | M5: =IF(AND(_xlfn.XLOOKUP(Tbl.PatRec[[#This Row],[Patient ID]],tblIPD[Patient id.],tblIPD[Patient id.],"")<>"",_xlfn.XLOOKUP(Tbl.PatRec[[#This Row],[Patient ID]],tblOPD[Patient id.],tblOPD[Patient id.],"")<>""),"OPD → IPD Transition","") | O5: =IFERROR(IF(Tbl.PatRec[[#This Row],[Current Condition]]="Admitted (IPD)",_xlfn.XLOOKUP(Tbl.PatRec[[#This Row],[Patient ID]],tblIPD[Patient id.],tblIPD[Net amount],""),IF(Tbl.PatRec[[#This Row],[Current Condition]]="Active OPD",_xlfn.XLOOKUP(Tbl.PatRec[[#This Row],[Patient ID]],tblOPD[Patient id.],tblOPD[Net amount],""),"")),"") -> 21090 | P5: Paid
A6: P-002 | B6: Name 2 | C6: 28433 | D6: =IF(C6="","",DATEDIF(C6,TODAY(),"Y")) -> 48 | E6: Male | F6: 44025 | G6: xxx-xxxxxxx | H6: xxx-xxxxxxx | I6: abc | J6: AB+ | K6: No | L6: =IF(_xlfn.XLOOKUP(Tbl.PatRec[[#This Row],[Patient ID]],tblIPD[Patient id.],tblIPD[Patient id.],"")<>"","Admitted (IPD)",IF(_xlfn.XLOOKUP(Tbl.PatRec[[#This Row],[Patient ID]],tblOPD[Patient id.],tblOPD[Patient id.],"")<>"","Active OPD","Registered")) -> Active OPD | M6: =IF(AND(_xlfn.XLOOKUP(Tbl.PatRec[[#This Row],[Patient ID]],tblIPD[Patient id.],tblIPD[Patient id.],"")<>"",_xlfn.XLOOKUP(Tbl.PatRec[[#This Row],[Patient ID]],tblOPD[Patient id.],tblOPD[Patient id.],"")<>""),"OPD → IPD Transition","") | N6: Active | O6: =IFERROR(IF(Tbl.PatRec[[#This Row],[Current Condition]]="Admitted (IPD)",_xlfn.XLOOKUP(Tbl.PatRec[[#This Row],[Patient ID]],tblIPD[Patient id.],tblIPD[Net amount],""),IF(Tbl.PatRec[[#This Row],[Current Condition]]="Active OPD",_xlfn.XLOOKUP(Tbl.PatRec[[#This Row],[Patient ID]],tblOPD[Patient id.],tblOPD[Net amount],""),"")),"")
A7: P-003 | B7: Name 3 | C7: 35392 | D7: =IF(C7="","",DATEDIF(C7,TODAY(),"Y")) -> 29 | E7: Male | F7: 45116 | G7: xxx-xxxxxxx | H7: xxx-xxxxxxx | I7: xyz | J7: B+ | K7: No | L7: =IF(_xlfn.XLOOKUP(Tbl.PatRec[[#This Row],[Patient ID]],tblIPD[Patient id.],tblIPD[Patient id.],"")<>"","Admitted (IPD)",IF(_xlfn.XLOOKUP(Tbl.PatRec[[#This Row],[Patient ID]],tblOPD[Patient id.],tblOPD[Patient id.],"")<>"","Active OPD","Registered")) -> Active OPD | M7: =IF(AND(_xlfn.XLOOKUP(Tbl.PatRec[[#This Row],[Patient ID]],tblIPD[Patient id.],tblIPD[Patient id.],"")<>"",_xlfn.XLOOKUP(Tbl.PatRec[[#This Row],[Patient ID]],tblOPD[Patient id.],tblOPD[Patient id.],"")<>""),"OPD → IPD Transition","") | O7: =IFERROR(IF(Tbl.PatRec[[#This Row],[Current Condition]]="Admitted (IPD)",_xlfn.XLOOKUP(Tbl.PatRec[[#This Row],[Patient ID]],tblIPD[Patient id.],tblIPD[Net amount],""),IF(Tbl.PatRec[[#This Row],[Current Condition]]="Active OPD",_xlfn.XLOOKUP(Tbl.PatRec[[#This Row],[Patient ID]],tblOPD[Patient id.],tblOPD[Net amount],""),"")),"")
A8: P-004 | B8: Name 4 | C8: 35089 | D8: =IF(C8="","",DATEDIF(C8,TODAY(),"Y")) -> 29 | E8: Female | F8: 44618 | G8: xxx-xxxxxxx | H8: xxx-xxxxxxx | I8: abc | J8: A | K8: Yes | L8: =IF(_xlfn.XLOOKUP(Tbl.PatRec[[#This Row],[Patient ID]],tblIPD[Patient id.],tblIPD[Patient id.],"")<>"","Admitted (IPD)",IF(_xlfn.XLOOKUP(Tbl.PatRec[[#This Row],[Patient ID]],tblOPD[Patient id.],tblOPD[Patient id.],"")<>"","Active OPD","Registered")) -> Admitted (IPD) | M8: =IF(AND(_xlfn.XLOOKUP(Tbl.PatRec[[#This Row],[Patient ID]],tblIPD[Patient id.],tblIPD[Patient id.],"")<>"",_xlfn.XLOOKUP(Tbl.PatRec[[#This Row],[Patient ID]],tblOPD[Patient id.],tblOPD[Patient id.],"")<>""),"OPD → IPD Transition","") | O8: =IFERROR(IF(Tbl.PatRec[[#This Row],[Current Condition]]="Admitted (IPD)",_xlfn.XLOOKUP(Tbl.PatRec[[#This Row],[Patient ID]],tblIPD[Patient id.],tblIPD[Net amount],""),IF(Tbl.PatRec[[#This Row],[Current Condition]]="Active OPD",_xlfn.XLOOKUP(Tbl.PatRec[[#This Row],[Patient ID]],tblOPD[Patient id.],tblOPD[Net amount],""),"")),"") -> 31635
A9: P-005 | B9: Name 5 | C9: 27320 | D9: =IF(C9="","",DATEDIF(C9,TODAY(),"Y")) -> 51 | E9: Male | F9: 45548 | G9: xxx-xxxxxxx | H9: xxx-xxxxxxx | I9: xyz | J9: B+ | K9: Yes | L9: =IF(_xlfn.XLOOKUP(Tbl.PatRec[[#This Row],[Patient ID]],tblIPD[Patient id.],tblIPD[Patient id.],"")<>"","Admitted (IPD)",IF(_xlfn.XLOOKUP(Tbl.PatRec[[#This Row],[Patient ID]],tblOPD[Patient id.],tblOPD[Patient id.],"")<>"","Active OPD","Registered")) -> Admitted (IPD) | M9: =IF(AND(_xlfn.XLOOKUP(Tbl.PatRec[[#This Row],[Patient ID]],tblIPD[Patient id.],tblIPD[Patient id.],"")<>"",_xlfn.XLOOKUP(Tbl.PatRec[[#This Row],[Patient ID]],tblOPD[Patient id.],tblOPD[Patient id.],"")<>""),"OPD → IPD Transition","") | O9: =IFERROR(IF(Tbl.PatRec[[#This Row],[Current Condition]]="Admitted (IPD)",_xlfn.XLOOKUP(Tbl.PatRec[[#This Row],[Patient ID]],tblIPD[Patient id.],tblIPD[Net amount],""),IF(Tbl.PatRec[[#This Row],[Current Condition]]="Active OPD",_xlfn.XLOOKUP(Tbl.PatRec[[#This Row],[Patient ID]],tblOPD[Patient id.],tblOPD[Net amount],""),"")),"") -> 59520
A10: P-006 | B10: Name 6 | C10: 30494 | D10: =IF(C10="","",DATEDIF(C10,TODAY(),"Y")) -> 42 | E10: Female | F10: 45165 | G10: xxx-xxxxxxx | H10: xxx-xxxxxxx | I10: abc | J10: O- | K10: Yes | L10: =IF(_xlfn.XLOOKUP(Tbl.PatRec[[#This Row],[Patient ID]],tblIPD[Patient id.],tblIPD[Patient id.],"")<>"","Admitted (IPD)",IF(_xlfn.XLOOKUP(Tbl.PatRec[[#This Row],[Patient ID]],tblOPD[Patient id.],tblOPD[Patient id.],"")<>"","Active OPD","Registered")) -> Active OPD | M10: =IF(AND(_xlfn.XLOOKUP(Tbl.PatRec[[#This Row],[Patient ID]],tblIPD[Patient id.],tblIPD[Patient id.],"")<>"",_xlfn.XLOOKUP(Tbl.PatRec[[#This Row],[Patient ID]],tblOPD[Patient id.],tblOPD[Patient id.],"")<>""),"OPD → IPD Transition","") | N10: Inactive | O10: =IFERROR(IF(Tbl.PatRec[[#This Row],[Current Condition]]="Admitted (IPD)",_xlfn.XLOOKUP(Tbl.PatRec[[#This Row],[Patient ID]],tblIPD[Patient id.],tblIPD[Net amount],""),IF(Tbl.PatRec[[#This Row],[Current Condition]]="Active OPD",_xlfn.XLOOKUP(Tbl.PatRec[[#This Row],[Patient ID]],tblOPD[Patient id.],tblOPD[Net amount],""),"")),"") -> 950
A11: P-007 | B11: Name 7 | C11: 39620 | D11: =IF(C11="","",DATEDIF(C11,TODAY(),"Y")) -> 17 | E11: Female | F11: 44990 | G11: xxx-xxxxxxx | H11: xxx-xxxxxxx | I11: xyz | J11: AB+ | K11: No | L11: =IF(_xlfn.XLOOKUP(Tbl.PatRec[[#This Row],[Patient ID]],tblIPD[Patient id.],tblIPD[Patient id.],"")<>"","Admitted (IPD)",IF(_xlfn.XLOOKUP(Tbl.PatRec[[#This Row],[Patient ID]],tblOPD[Patient id.],tblOPD[Patient id.],"")<>"","Active OPD","Registered")) -> Admitted (IPD) | M11: =IF(AND(_xlfn.XLOOKUP(Tbl.PatRec[[#This Row],[Patient ID]],tblIPD[Patient id.],tblIPD[Patient id.],"")<>"",_xlfn.XLOOKUP(Tbl.PatRec[[#This Row],[Patient ID]],tblOPD[Patient id.],tblOPD[Patient id.],"")<>""),"OPD → IPD Transition","") | O11: =IFERROR(IF(Tbl.PatRec[[#This Row],[Current Condition]]="Admitted (IPD)",_xlfn.XLOOKUP(Tbl.PatRec[[#This Row],[Patient ID]],tblIPD[Patient id.],tblIPD[Net amount],""),IF(Tbl.PatRec[[#This Row],[Current Condition]]="Active OPD",_xlfn.XLOOKUP(Tbl.PatRec[[#This Row],[Patient ID]],tblOPD[Patient id.],tblOPD[Net amount],""),"")),"") -> 409768
A12: P-008 | B12: Name 8 | C12: 30970 | D12: =IF(C12="","",DATEDIF(C12,TODAY(),"Y")) -> 41 | E12: Female | F12: 44882 | G12: xxx-xxxxxxx | H12: xxx-xxxxxxx | I12: abc | J12: O- | K12: No | L12: =IF(_xlfn.XLOOKUP(Tbl.PatRec[[#This Row],[Patient ID]],tblIPD[Patient id.],tblIPD[Patient id.],"")<>"","Admitted (IPD)",IF(_xlfn.XLOOKUP(Tbl.PatRec[[#This Row],[Patient ID]],tblOPD[Patient id.],tblOPD[Patient id.],"")<>"","Active OPD","Registered")) -> Admitted (IPD) | M12: =IF(AND(_xlfn.XLOOKUP(Tbl.PatRec[[#This Row],[Patient ID]],tblIPD[Patient id.],tblIPD[Patient id.],"")<>"",_xlfn.XLOOKUP(Tbl.PatRec[[#This Row],[Patient ID]],tblOPD[Patient id.],tblOPD[Patient id.],"")<>""),"OPD → IPD Transition","") -> OPD → IPD Transition | O12: =IFERROR(IF(Tbl.PatRec[[#This Row],[Current Condition]]="Admitted (IPD)",_xlfn.XLOOKUP(Tbl.PatRec[[#This Row],[Patient ID]],tblIPD[Patient id.],tblIPD[Net amount],""),IF(Tbl.PatRec[[#This Row],[Current Condition]]="Active OPD",_xlfn.XLOOKUP(Tbl.PatRec[[#This Row],[Patient ID]],tblOPD[Patient id.],tblOPD[Net amount],""),"")),"")
A13: P-009 | B13: Name 9 | C13: 31976 | D13: =IF(C13="","",DATEDIF(C13,TODAY(),"Y")) -> 38 | E13: Male | F13: 44042 | G13: xxx-xxxxxxx | H13: xxx-xxxxxxx | I13: xyz | J13: B+ | K13: No | L13: =IF(_xlfn.XLOOKUP(Tbl.PatRec[[#This Row],[Patient ID]],tblIPD[Patient id.],tblIPD[Patient id.],"")<>"","Admitted (IPD)",IF(_xlfn.XLOOKUP(Tbl.PatRec[[#This Row],[Patient ID]],tblOPD[Patient id.],tblOPD[Patient id.],"")<>"","Active OPD","Registered")) -> Admitted (IPD) | M13: =IF(AND(_xlfn.XLOOKUP(Tbl.PatRec[[#This Row],[Patient ID]],tblIPD[Patient id.],tblIPD[Patient id.],"")<>"",_xlfn.XLOOKUP(Tbl.PatRec[[#This Row],[Patient ID]],tblOPD[Patient id.],tblOPD[Patient id.],"")<>""),"OPD → IPD Transition","") | O13: =IFERROR(IF(Tbl.PatRec[[#This Row],[Current Condition]]="Admitted (IPD)",_xlfn.XLOOKUP(Tbl.PatRec[[#This Row],[Patient ID]],tblIPD[Patient id.],tblIPD[Net amount],""),IF(Tbl.PatRec[[#This Row],[Current Condition]]="Active OPD",_xlfn.XLOOKUP(Tbl.PatRec[[#This Row],[Patient ID]],tblOPD[Patient id.],tblOPD[Net amount],""),"")),"") -> 178920
A14: P-010 | B14: Name 10 | C14: 29791 | D14: =IF(C14="","",DATEDIF(C14,TODAY(),"Y")) -> 44 | E14: Female | F14: 45212 | G14: xxx-xxxxxxx | H14: xxx-xxxxxxx | I14: abc | J14: B+ | K14: No | L14: =IF(_xlfn.XLOOKUP(Tbl.PatRec[[#This Row],[Patient ID]],tblIPD[Patient id.],tblIPD[Patient id.],"")<>"","Admitted (IPD)",IF(_xlfn.XLOOKUP(Tbl.PatRec[[#This Row],[Patient ID]],tblOPD[Patient id.],tblOPD[Patient id.],"")<>"","Active OPD","Registered")) -> Active OPD | M14: =IF(AND(_xlfn.XLOOKUP(Tbl.PatRec[[#This Row],[Patient ID]],tblIPD[Patient id.],tblIPD[Patient id.],"")<>"",_xlfn.XLOOKUP(Tbl.PatRec[[#This Row],[Patient ID]],tblOPD[Patient id.],tblOPD[Patient id.],"")<>""),"OPD → IPD Transition","") | O14: =IFERROR(IF(Tbl.PatRec[[#This Row],[Current Condition]]="Admitted (IPD)",_xlfn.XLOOKUP(Tbl.PatRec[[#This Row],[Patient ID]],tblIPD[Patient id.],tblIPD[Net amount],""),IF(Tbl.PatRec[[#This Row],[Current Condition]]="Active OPD",_xlfn.XLOOKUP(Tbl.PatRec[[#This Row],[Patient ID]],tblOPD[Patient id.],tblOPD[Net amount],""),"")),"") -> 2300
A15: P-011 | B15: Name 11 | C15: 35457 | D15: =IF(C15="","",DATEDIF(C15,TODAY(),"Y")) -> 28 | E15: Male | F15: 44047 | G15: xxx-xxxxxxx | H15: xxx-xxxxxxx | I15: xyz | J15: A+ | K15: Yes | L15: =IF(_xlfn.XLOOKUP(Tbl.PatRec[[#This Row],[Patient ID]],tblIPD[Patient id.],tblIPD[Patient id.],"")<>"","Admitted (IPD)",IF(_xlfn.XLOOKUP(Tbl.PatRec[[#This Row],[Patient ID]],tblOPD[Patient id.],tblOPD[Patient id.],"")<>"","Active OPD","Registered")) -> Admitted (IPD) | M15: =IF(AND(_xlfn.XLOOKUP(Tbl.PatRec[[#This Row],[Patient ID]],tblIPD[Patient id.],tblIPD[Patient id.],"")<>"",_xlfn.XLOOKUP(Tbl.PatRec[[#This Row],[Patient ID]],tblOPD[Patient id.],tblOPD[Patient id.],"")<>""),"OPD → IPD Transition","") | O15: =IFERROR(IF(Tbl.PatRec[[#This Row],[Current Condition]]="Admitted (IPD)",_xlfn.XLOOKUP(Tbl.PatRec[[#This Row],[Patient ID]],tblIPD[Patient id.],tblIPD[Net amount],""),IF(Tbl.PatRec[[#This Row],[Current Condition]]="Active OPD",_xlfn.XLOOKUP(Tbl.PatRec[[#This Row],[Patient ID]],tblOPD[Patient id.],tblOPD[Net amount],""),"")),"") -> 115020
A16: P-012 | B16: Name 12 | C16: 22998 | D16: =IF(C16="","",DATEDIF(C16,TODAY(),"Y")) -> 63 | E16: Male | F16: 44024 | G16: xxx-xxxxxxx | H16: xxx-xxxxxxx | I16: abc | J16: AB+ | K16: Yes | L16: =IF(_xlfn.XLOOKUP(Tbl.PatRec[[#This Row],[Patient ID]],tblIPD[Patient id.],tblIPD[Patient id.],"")<>"","Admitted (IPD)",IF(_xlfn.XLOOKUP(Tbl.PatRec[[#This Row],[Patient ID]],tblOPD[Patient id.],tblOPD[Patient id.],"")<>"","Active OPD","Registered")) -> Active OPD | M16: =IF(AND(_xlfn.XLOOKUP(Tbl.PatRec[[#This Row],[Patient ID]],tblIPD[Patient id.],tblIPD[Patient id.],"")<>"",_xlfn.XLOOKUP(Tbl.PatRec[[#This Row],[Patient ID]],tblOPD[Patient id.],tblOPD[Patient id.],"")<>""),"OPD → IPD Transition","") | O16: =IFERROR(IF(Tbl.PatRec[[#This Row],[Current Condition]]="Admitted (IPD)",_xlfn.XLOOKUP(Tbl.PatRec[[#This Row],[Patient ID]],tblIPD[Patient id.],tblIPD[Net amount],""),IF(Tbl.PatRec[[#This Row],[Current Condition]]="Active OPD",_xlfn.XLOOKUP(Tbl.PatRec[[#This Row],[Patient ID]],tblOPD[Patient id.],tblOPD[Net amount],""),"")),"") -> 1900
A17: P-013 | B17: Name 13 | C17: 39722 | D17: =IF(C17="","",DATEDIF(C17,TODAY(),"Y")) -> 17 | E17: Female | F17: 43976 | G17: xxx-xxxxxxx | H17: xxx-xxxxxxx | I17: xyz | J17: B+ | K17: Yes | L17: =IF(_xlfn.XLOOKUP(Tbl.PatRec[[#This Row],[Patient ID]],tblIPD[Patient id.],tblIPD[Patient id.],"")<>"","Admitted (IPD)",IF(_xlfn.XLOOKUP(Tbl.PatRec[[#This Row],[Patient ID]],tblOPD[Patient id.],tblOPD[Patient id.],"")<>"","Active OPD","Registered")) -> Admitted (IPD) | M17: =IF(AND(_xlfn.XLOOKUP(Tbl.PatRec[[#This Row],[Patient ID]],tblIPD[Patient id.],tblIPD[Patient id.],"")<>"",_xlfn.XLOOKUP(Tbl.PatRec[[#This Row],[Patient ID]],tblOPD[Patient id.],tblOPD[Patient id.],"")<>""),"OPD → IPD Transition","") | O17: =IFERROR(IF(Tbl.PatRec[[#This Row],[Current Condition]]="Admitted (IPD)",_xlfn.XLOOKUP(Tbl.PatRec[[#This Row],[Patient ID]],tblIPD[Patient id.],tblIPD[Net amount],""),IF(Tbl.PatRec[[#This Row],[Current Condition]]="Active OPD",_xlfn.XLOOKUP(Tbl.PatRec[[#This Row],[Patient ID]],tblOPD[Patient id.],tblOPD[Net amount],""),"")),"") -> 28120
A18: P-014 | B18: Name 14 | C18: 26673 | D18: =IF(C18="","",DATEDIF(C18,TODAY(),"Y")) -> 52 | E18: Male | F18: 45108 | G18: xxx-xxxxxxx | H18: xxx-xxxxxxx | I18: abc | J18: A | K18: Yes | L18: =IF(_xlfn.XLOOKUP(Tbl.PatRec[[#This Row],[Patient ID]],tblIPD[Patient id.],tblIPD[Patient id.],"")<>"","Admitted (IPD)",IF(_xlfn.XLOOKUP(Tbl.PatRec[[#This Row],[Patient ID]],tblOPD[Patient id.],tblOPD[Patient id.],"")<>"","Active OPD","Registered")) -> Admitted (IPD) | M18: =IF(AND(_xlfn.XLOOKUP(Tbl.PatRec[[#This Row],[Patient ID]],tblIPD[Patient id.],tblIPD[Patient id.],"")<>"",_xlfn.XLOOKUP(Tbl.PatRec[[#This Row],[Patient ID]],tblOPD[Patient id.],tblOPD[Patient id.],"")<>""),"OPD → IPD Transition","") -> OPD → IPD Transition | O18: =IFERROR(IF(Tbl.PatRec[[#This Row],[Current Condition]]="Admitted (IPD)",_xlfn.XLOOKUP(Tbl.PatRec[[#This Row],[Patient ID]],tblIPD[Patient id.],tblIPD[Net amount],""),IF(Tbl.PatRec[[#This Row],[Current Condition]]="Active OPD",_xlfn.XLOOKUP(Tbl.PatRec[[#This Row],[Patient ID]],tblOPD[Patient id.],tblOPD[Net amount],""),"")),"")
A19: P-015 | B19: Name 15 | C19: 32446 | D19: =IF(C19="","",DATEDIF(C19,TODAY(),"Y")) -> 37 | E19: Female | F19: 44341 | G19: xxx-xxxxxxx | H19: xxx-xxxxxxx | I19: xyz | J19: B+ | K19: Yes | L19: =IF(_xlfn.XLOOKUP(Tbl.PatRec[[#This Row],[Patient ID]],tblIPD[Patient id.],tblIPD[Patient id.],"")<>"","Admitted (IPD)",IF(_xlfn.XLOOKUP(Tbl.PatRec[[#This Row],[Patient ID]],tblOPD[Patient id.],tblOPD[Patient id.],"")<>"","Active OPD","Registered")) -> Admitted (IPD) | M19: =IF(AND(_xlfn.XLOOKUP(Tbl.PatRec[[#This Row],[Patient ID]],tblIPD[Patient id.],tblIPD[Patient id.],"")<>"",_xlfn.XLOOKUP(Tbl.PatRec[[#This Row],[Patient ID]],tblOPD[Patient id.],tblOPD[Patient id.],"")<>""),"OPD → IPD Transition","") | O19: =IFERROR(IF(Tbl.PatRec[[#This Row],[Current Condition]]="Admitted (IPD)",_xlfn.XLOOKUP(Tbl.PatRec[[#This Row],[Patient ID]],tblIPD[Patient id.],tblIPD[Net amount],""),IF(Tbl.PatRec[[#This Row],[Current Condition]]="Active OPD",_xlfn.XLOOKUP(Tbl.PatRec[[#This Row],[Patient ID]],tblOPD[Patient id.],tblOPD[Net amount],""),"")),"") -> 477375
A20: P-016 | B20: Name 16 | C20: 39737 | D20: =IF(C20="","",DATEDIF(C20,TODAY(),"Y")) -> 17 | E20: Female | F20: 45128 | G20: xxx-xxxxxxx | H20: xxx-xxxxxxx | I20: abc | J20: O- | K20: No | L20: =IF(_xlfn.XLOOKUP(Tbl.PatRec[[#This Row],[Patient ID]],tblIPD[Patient id.],tblIPD[Patient id.],"")<>"","Admitted (IPD)",IF(_xlfn.XLOOKUP(Tbl.PatRec[[#This Row],[Patient ID]],tblOPD[Patient id.],tblOPD[Patient id.],"")<>"","Active OPD","Registered")) -> Active OPD | M20: =IF(AND(_xlfn.XLOOKUP(Tbl.PatRec[[#This Row],[Patient ID]],tblIPD[Patient id.],tblIPD[Patient id.],"")<>"",_xlfn.XLOOKUP(Tbl.PatRec[[#This Row],[Patient ID]],tblOPD[Patient id.],tblOPD[Patient id.],"")<>""),"OPD → IPD Transition","") | O20: =IFERROR(IF(Tbl.PatRec[[#This Row],[Current Condition]]="Admitted (IPD)",_xlfn.XLOOKUP(Tbl.PatRec[[#This Row],[Patient ID]],tblIPD[Patient id.],tblIPD[Net amount],""),IF(Tbl.PatRec[[#This Row],[Current Condition]]="Active OPD",_xlfn.XLOOKUP(Tbl.PatRec[[#This Row],[Patient ID]],tblOPD[Patient id.],tblOPD[Net amount],""),"")),"") -> 2300
A21: P-017 | B21: Name 17 | C21: 26274 | D21: =IF(C21="","",DATEDIF(C21,TODAY(),"Y")) -> 54 | E21: Male | F21: 44324 | G21: xxx-xxxxxxx | H21: xxx-xxxxxxx | I21: xyz | J21: AB+ | K21: Yes | L21: =IF(_xlfn.XLOOKUP(Tbl.PatRec[[#This Row],[Patient ID]],tblIPD[Patient id.],tblIPD[Patient id.],"")<>"","Admitted (IPD)",IF(_xlfn.XLOOKUP(Tbl.PatRec[[#This Row],[Patient ID]],tblOPD[Patient id.],tblOPD[Patient id.],"")<>"","Active OPD","Registered")) -> Admitted (IPD) | M21: =IF(AND(_xlfn.XLOOKUP(Tbl.PatRec[[#This Row],[Patient ID]],tblIPD[Patient id.],tblIPD[Patient id.],"")<>"",_xlfn.XLOOKUP(Tbl.PatRec[[#This Row],[Patient ID]],tblOPD[Patient id.],tblOPD[Patient id.],"")<>""),"OPD → IPD Transition","") | O21: =IFERROR(IF(Tbl.PatRec[[#This Row],[Current Condition]]="Admitted (IPD)",_xlfn.XLOOKUP(Tbl.PatRec[[#This Row],[Patient ID]],tblIPD[Patient id.],tblIPD[Net amount],""),IF(Tbl.PatRec[[#This Row],[Current Condition]]="Active OPD",_xlfn.XLOOKUP(Tbl.PatRec[[#This Row],[Patient ID]],tblOPD[Patient id.],tblOPD[Net amount],""),"")),"") -> 21090
A22: P-018 | B22: Name 18 | C22: 37666 | D22: =IF(C22="","",DATEDIF(C22,TODAY(),"Y")) -> 22 | E22: Female | F22: 45533 | G22: xxx-xxxxxxx | H22: xxx-xxxxxxx | I22: abc | J22: O- | K22: No | L22: =IF(_xlfn.XLOOKUP(Tbl.PatRec[[#This Row],[Patient ID]],tblIPD[Patient id.],tblIPD[Patient id.],"")<>"","Admitted (IPD)",IF(_xlfn.XLOOKUP(Tbl.PatRec[[#This Row],[Patient ID]],tblOPD[Patient id.],tblOPD[Patient id.],"")<>"","Active OPD","Registered")) -> Active OPD | M22: =IF(AND(_xlfn.XLOOKUP(Tbl.PatRec[[#This Row],[Patient ID]],tblIPD[Patient id.],tblIPD[Patient id.],"")<>"",_xlfn.XLOOKUP(Tbl.PatRec[[#This Row],[Patient ID]],tblOPD[Patient id.],tblOPD[Patient id.],"")<>""),"OPD → IPD Transition","") | O22: =IFERROR(IF(Tbl.PatRec[[#This Row],[Current Condition]]="Admitted (IPD)",_xlfn.XLOOKUP(Tbl.PatRec[[#This Row],[Patient ID]],tblIPD[Patient id.],tblIPD[Net amount],""),IF(Tbl.PatRec[[#This Row],[Current Condition]]="Active OPD",_xlfn.XLOOKUP(Tbl.PatRec[[#This Row],[Patient ID]],tblOPD[Patient id.],tblOPD[Net amount],""),"")),"") -> 2000
... A24: P-020 | B24: Name 20 | C24: 33639 | D24: =IF(C24="","",DATEDIF(C24,TODAY(),"Y")) -> 33 | E24: Male | F24: 43958 | G24: xxx-xxxxxxx | H24: xxx-xxxxxxx | I24: abc | J24: B+ | K24: Yes | L24: =IF(_xlfn.XLOOKUP(Tbl.PatRec[[#This Row],[Patient ID]],tblIPD[Patient id.],tblIPD[Patient id.],"")<>"","Admitted (IPD)",IF(_xlfn.XLOOKUP(Tbl.PatRec[[#This Row],[Patient ID]],tblOPD[Patient id.],tblOPD[Patient id.],"")<>"","Active OPD","Registered")) -> Active OPD | M24: =IF(AND(_xlfn.XLOOKUP(Tbl.PatRec[[#This Row],[Patient ID]],tblIPD[Patient id.],tblIPD[Patient id.],"")<>"",_xlfn.XLOOKUP(Tbl.PatRec[[#This Row],[Patient ID]],tblOPD[Patient id.],tblOPD[Patient id.],"")<>""),"OPD → IPD Transition","") | O24: =IFERROR(IF(Tbl.PatRec[[#This Row],[Current Condition]]="Admitted (IPD)",_xlfn.XLOOKUP(Tbl.PatRec[[#This Row],[Patient ID]],tblIPD[Patient id.],tblIPD[Net amount],""),IF(Tbl.PatRec[[#This Row],[Current Condition]]="Active OPD",_xlfn.XLOOKUP(Tbl.PatRec[[#This Row],[Patient ID]],tblOPD[Patient id.],tblOPD[Net amount],""),"")),"") -> 29750

Sheet  OPD Billing 
F1: OPD Billing Records
A4: Invoice No. | B4: Patient Name | C4: Patient id. | D4: Current status | E4: Bill type | F4: Quantity | G4: Amount | H4: Status | I4: Payment Method | J4: Paid date | K4: Discount | L4: Net amount | M4: Remarks
A5: INV.OPD-1 | B5: =_xlfn.XLOOKUP(tblOPD[[#This Row],[Patient id.]],Tbl.PatRec[Patient ID],Tbl.PatRec[Name],"",0) -> Name 10 | C5: P-010 | D5: =IF(_xlfn.XLOOKUP(tblOPD[[#This Row],[Patient id.]],tblIPD[Patient id.],tblIPD[Patient id.],"")<>"","OPD → IPD Transition","OPD") -> OPD | E5: Consultation (Specialist/Professor) | G5: =IFERROR(VLOOKUP(tblOPD[[#This Row],[Bill type ]],'Reference Lists'!$A$25:$B$38,2,FALSE)*MAX(1,tblOPD[[#This Row],[Quantity]]),"") -> 2500 | H5: Paid | I5: Cash | J5: =TODAY() -> 46027 | K5: =IFERROR((VLOOKUP(tblOPD[[#This Row],[Bill type ]],'Reference Lists'!$A$24:$D$38,4,FALSE))*tblOPD[[#This Row],[Amount]],"") -> 200 | L5: =IFERROR(tblOPD[[#This Row],[Amount]]-tblOPD[[#This Row],[Discount]],"") -> 2300
A6: INV.OPD-2 | B6: =_xlfn.XLOOKUP(tblOPD[[#This Row],[Patient id.]],Tbl.PatRec[Patient ID],Tbl.PatRec[Name],"",0) -> Name 6 | C6: P-006 | D6: =IF(_xlfn.XLOOKUP(tblOPD[[#This Row],[Patient id.]],tblIPD[Patient id.],tblIPD[Patient id.],"")<>"","OPD → IPD Transition","OPD") -> OPD | E6: Consultation (General) | G6: =IFERROR(VLOOKUP(tblOPD[[#This Row],[Bill type ]],'Reference Lists'!$A$25:$B$38,2,FALSE)*MAX(1,tblOPD[[#This Row],[Quantity]]),"") -> 1000 | H6: Paid | I6: Card | J6: =TODAY() -> 46027 | K6: =IFERROR((VLOOKUP(tblOPD[[#This Row],[Bill type ]],'Reference Lists'!$A$24:$D$38,4,FALSE))*tblOPD[[#This Row],[Amount]],"") -> 50 | L6: =IFERROR(tblOPD[[#This Row],[Amount]]-tblOPD[[#This Row],[Discount]],"") -> 950
A7: INV.OPD-3 | B7: =_xlfn.XLOOKUP(tblOPD[[#This Row],[Patient id.]],Tbl.PatRec[Patient ID],Tbl.PatRec[Name],"",0) -> Name 12 | C7: P-012 | D7: =IF(_xlfn.XLOOKUP(tblOPD[[#This Row],[Patient id.]],tblIPD[Patient id.],tblIPD[Patient id.],"")<>"","OPD → IPD Transition","OPD") -> OPD | E7: Stitch Removal | F7: 2 | G7: =IFERROR(VLOOKUP(tblOPD[[#This Row],[Bill type ]],'Reference Lists'!$A$25:$B$38,2,FALSE)*MAX(1,tblOPD[[#This Row],[Quantity]]),"") -> 2000 | H7: Paid | I7: Cash | J7: =TODAY() -> 46027 | K7: =IFERROR((VLOOKUP(tblOPD[[#This Row],[Bill type ]],'Reference Lists'!$A$24:$D$38,4,FALSE))*tblOPD[[#This Row],[Amount]],"") -> 100 | L7: =IFERROR(tblOPD[[#This Row],[Amount]]-tblOPD[[#This Row],[Discount]],"") -> 1900
A8: INV.OPD-4 | B8: =_xlfn.XLOOKUP(tblOPD[[#This Row],[Patient id.]],Tbl.PatRec[Patient ID],Tbl.PatRec[Name],"",0) -> Name 3 | C8: P-003 | D8: =IF(_xlfn.XLOOKUP(tblOPD[[#This Row],[Patient id.]],tblIPD[Patient id.],tblIPD[Patient id.],"")<>"","OPD → IPD Transition","OPD") -> OPD | E8: Injection (IM/IV) | G8: =IFERROR(VLOOKUP(tblOPD[[#This Row],[Bill type ]],'Reference Lists'!$A$25:$B$38,2,FALSE)*MAX(1,tblOPD[[#This Row],[Quantity]]),"") | H8: Paid | I8: Card | J8: =TODAY() -> 46027 | K8: =IFERROR((VLOOKUP(tblOPD[[#This Row],[Bill type ]],'Reference Lists'!$A$24:$D$38,4,FALSE))*tblOPD[[#This Row],[Amount]],"") | L8: =IFERROR(tblOPD[[#This Row],[Amount]]-tblOPD[[#This Row],[Discount]],"")
A9: INV.OPD-5 | B9: =_xlfn.XLOOKUP(tblOPD[[#This Row],[Patient id.]],Tbl.PatRec[Patient ID],Tbl.PatRec[Name],"",0) -> Name 14 | C9: P-014 | D9: =IF(_xlfn.XLOOKUP(tblOPD[[#This Row],[Patient id.]],tblIPD[Patient id.],tblIPD[Patient id.],"")<>"","OPD → IPD Transition","OPD") -> OPD → IPD Transition | E9: Ultrasound | F9: 2 | G9: =IFERROR(VLOOKUP(tblOPD[[#This Row],[Bill type ]],'Reference Lists'!$A$25:$B$38,2,FALSE)*MAX(1,tblOPD[[#This Row],[Quantity]]),"") -> 5000 | H9: Paid | I9: Card | J9: =TODAY() -> 46027 | K9: =IFERROR((VLOOKUP(tblOPD[[#This Row],[Bill type ]],'Reference Lists'!$A$24:$D$38,4,FALSE))*tblOPD[[#This Row],[Amount]],"") -> 400 | L9: =IFERROR(tblOPD[[#This Row],[Amount]]-tblOPD[[#This Row],[Discount]],"") -> 4600
A10: INV.OPD-6 | B10: =_xlfn.XLOOKUP(tblOPD[[#This Row],[Patient id.]],Tbl.PatRec[Patient ID],Tbl.PatRec[Name],"",0) -> Name 2 | C10: P-002 | D10: =IF(_xlfn.XLOOKUP(tblOPD[[#This Row],[Patient id.]],tblIPD[Patient id.],tblIPD[Patient id.],"")<>"","OPD → IPD Transition","OPD") -> OPD | E10: Nebulization | F10: 3 | G10: =IFERROR(VLOOKUP(tblOPD[[#This Row],[Bill type ]],'Reference Lists'!$A$25:$B$38,2,FALSE)*MAX(1,tblOPD[[#This Row],[Quantity]]),"") | H10: Paid | I10: Cash | J10: =TODAY() -> 46027 | K10: =IFERROR((VLOOKUP(tblOPD[[#This Row],[Bill type ]],'Reference Lists'!$A$24:$D$38,4,FALSE))*tblOPD[[#This Row],[Amount]],"") | L10: =IFERROR(tblOPD[[#This Row],[Amount]]-tblOPD[[#This Row],[Discount]],"")
A11: INV.OPD-7 | B11: =_xlfn.XLOOKUP(tblOPD[[#This Row],[Patient id.]],Tbl.PatRec[Patient ID],Tbl.PatRec[Name],"",0) -> Name 16 | C11: P-016 | D11: =IF(_xlfn.XLOOKUP(tblOPD[[#This Row],[Patient id.]],tblIPD[Patient id.],tblIPD[Patient id.],"")<>"","OPD → IPD Transition","OPD") -> OPD | E11: Consultation (Specialist/Professor) | G11: =IFERROR(VLOOKUP(tblOPD[[#This Row],[Bill type ]],'Reference Lists'!$A$25:$B$38,2,FALSE)*MAX(1,tblOPD[[#This Row],[Quantity]]),"") -> 2500 | H11: Paid | I11: Cash | J11: =TODAY() -> 46027 | K11: =IFERROR((VLOOKUP(tblOPD[[#This Row],[Bill type ]],'Reference Lists'!$A$24:$D$38,4,FALSE))*tblOPD[[#This Row],[Amount]],"") -> 200 | L11: =IFERROR(tblOPD[[#This Row],[Amount]]-tblOPD[[#This Row],[Discount]],"") -> 2300
A12: INV.OPD-8 | B12: =_xlfn.XLOOKUP(tblOPD[[#This Row],[Patient id.]],Tbl.PatRec[Patient ID],Tbl.PatRec[Name],"",0) -> Name 18 | C12: P-018 | D12: =IF(_xlfn.XLOOKUP(tblOPD[[#This Row],[Patient id.]],tblIPD[Patient id.],tblIPD[Patient id.],"")<>"","OPD → IPD Transition","OPD") -> OPD | E12: Dressing (Minor) | F12: 4 | G12: =IFERROR(VLOOKUP(tblOPD[[#This Row],[Bill type ]],'Reference Lists'!$A$25:$B$38,2,FALSE)*MAX(1,tblOPD[[#This Row],[Quantity]]),"") -> 2000 | H12: Paid | I12: Card | J12: =TODAY() -> 46027 | K12: =IFERROR((VLOOKUP(tblOPD[[#This Row],[Bill type ]],'Reference Lists'!$A$24:$D$38,4,FALSE))*tblOPD[[#This Row],[Amount]],"") -> 0 | L12: =IFERROR(tblOPD[[#This Row],[Amount]]-tblOPD[[#This Row],[Discount]],"") -> 2000
A13: INV.OPD-9 | B13: =_xlfn.XLOOKUP(tblOPD[[#This Row],[Patient id.]],Tbl.PatRec[Patient ID],Tbl.PatRec[Name],"",0) -> Name 20 | C13: P-020 | D13: =IF(_xlfn.XLOOKUP(tblOPD[[#This Row],[Patient id.]],tblIPD[Patient id.],tblIPD[Patient id.],"")<>"","OPD → IPD Transition","OPD") -> OPD | E13: C-Section | G13: =IFERROR(VLOOKUP(tblOPD[[#This Row],[Bill type ]],'Reference Lists'!$A$25:$B$38,2,FALSE)*MAX(1,tblOPD[[#This Row],[Quantity]]),"") -> 35000 | H13: Paid | I13: Insurance | J13: =TODAY() -> 46027 | K13: =IFERROR((VLOOKUP(tblOPD[[#This Row],[Bill type ]],'Reference Lists'!$A$24:$D$38,4,FALSE))*tblOPD[[#This Row],[Amount]],"") -> 5250 | L13: =IFERROR(tblOPD[[#This Row],[Amount]]-tblOPD[[#This Row],[Discount]],"") -> 29750
A14: INV.OPD-10 | B14: =_xlfn.XLOOKUP(tblOPD[[#This Row],[Patient id.]],Tbl.PatRec[Patient ID],Tbl.PatRec[Name],"",0) -> Name 8 | C14: P-008 | D14: =IF(_xlfn.XLOOKUP(tblOPD[[#This Row],[Patient id.]],tblIPD[Patient id.],tblIPD[Patient id.],"")<>"","OPD → IPD Transition","OPD") -> OPD → IPD Transition | G14: =IFERROR(VLOOKUP(tblOPD[[#This Row],[Bill type ]],'Reference Lists'!$A$25:$B$38,2,FALSE)*MAX(1,tblOPD[[#This Row],[Quantity]]),"") | J14: =TODAY() -> 46027 | K14: =IFERROR((VLOOKUP(tblOPD[[#This Row],[Bill type ]],'Reference Lists'!$A$24:$D$38,4,FALSE))*tblOPD[[#This Row],[Amount]],"") | L14: =IFERROR(tblOPD[[#This Row],[Amount]]-tblOPD[[#This Row],[Discount]],"")

Sheet IPD Billing
G1: IPD Billing Record
A4: Invoice No. | B4: Patient id. | C4: Name | D4: Ward type | E4: Bed No. | F4: Admission date | G4: Discharge date | H4: No. of days | I4: Rate per day | J4: Room Charges | K4: Nursing charges | L4: Doctor charges | M4: Other charges | N4: Total Amount | O4: Status | P4: Payment Method | Q4: Payment date | R4: Discount | S4: Net amount | T4: Remarks
A5: INV.IPD-1 | B5: P-001 | C5: =_xlfn.XLOOKUP(tblIPD[[#This Row],[Patient id.]],Tbl.PatRec[Patient ID],Tbl.PatRec[Name],"",0) -> Name 1 | D5: General | E5: 3 | F5: 46006 | G5: 46011 | H5: =tblIPD[[#This Row],[Discharge date]]-tblIPD[[#This Row],[Admission date ]]+1 -> 6 | I5: =IF(tblIPD[[#This Row],[Ward type ]]="General",'Reference Lists'!$I$13,IF(tblIPD[[#This Row],[Ward type ]]="Semi-Private",'Reference Lists'!$I$14,IF(tblIPD[[#This Row],[Ward type ]]="Private",'Reference Lists'!$I$15,IF(tblIPD[[#This Row],[Ward type ]]="ICU",'Reference Lists'!$I$17,IF(tblIPD[[#This Row],[Ward type ]]="CCU",'Reference Lists'!$I$16,""))))) -> 2000 | J5: =IF(tblIPD[[#This Row],[Ward type ]]="General",'Reference Lists'!$B$13,IF(tblIPD[[#This Row],[Ward type ]]="Semi-Private",'Reference Lists'!$B$14,IF(tblIPD[[#This Row],[Ward type ]]="Private",'Reference Lists'!$B$15,IF(tblIPD[[#This Row],[Ward type ]]="ICU",'Reference Lists'!$B$16,IF(tblIPD[[#This Row],[Ward type ]]="CCU",'Reference Lists'!$B$17,""))))) -> 700 | K5: =IF(tblIPD[[#This Row],[Ward type ]]="General",'Reference Lists'!$E$4,IF(tblIPD[[#This Row],[Ward type ]]="Semi-Private",'Reference Lists'!$E$5,IF(tblIPD[[#This Row],[Ward type ]]="Private",'Reference Lists'!$E$6,IF(tblIPD[[#This Row],[Ward type ]]="ICU",'Reference Lists'!$B$16,IF(tblIPD[[#This Row],[Ward type ]]="CCU",'Reference Lists'!$B$17,""))))) -> 500 | L5: =IF(tblIPD[[#This Row],[Ward type ]]="General",'Reference Lists'!$E$13,IF(tblIPD[[#This Row],[Ward type ]]="Semi-Private",'Reference Lists'!$E$14,IF(tblIPD[[#This Row],[Ward type ]]="Private",'Reference Lists'!$E$15,IF(tblIPD[[#This Row],[Ward type ]]="ICU",'Reference Lists'!$E$16,IF(tblIPD[[#This Row],[Ward type ]]="CCU",'Reference Lists'!$E$17,""))))) -> 500 | N5: =(tblIPD[[#This Row],[Other charges]]+tblIPD[[#This Row],[Doctor charges]]+tblIPD[[#This Row],[Nursing charges]]+tblIPD[[#This Row],[Room Charges]]+tblIPD[[#This Row],[Rate per day]])*tblIPD[[#This Row],[No. of days]] -> 22200 | O5: Paid | P5: Cash | Q5: 46011 | R5: =tblIPD[[#This Row],[Total Amount]]*VLOOKUP(tblIPD[[#This Row],[Ward type ]],'Reference Lists'!$A$4:$B$8,2,FALSE) -> 1110 | S5: =tblIPD[[#This Row],[Total Amount]]-tblIPD[[#This Row],[Discount]] -> 21090
A6: INV.IPD-2 | B6: P-005 | C6: =_xlfn.XLOOKUP(tblIPD[[#This Row],[Patient id.]],Tbl.PatRec[Patient ID],Tbl.PatRec[Name],"",0) -> Name 5 | D6: Semi-Private | E6: 9 | F6: 46006 | G6: 46013 | H6: =tblIPD[[#This Row],[Discharge date]]-tblIPD[[#This Row],[Admission date ]]+1 -> 8 | I6: =IF(tblIPD[[#This Row],[Ward type ]]="General",'Reference Lists'!$I$13,IF(tblIPD[[#This Row],[Ward type ]]="Semi-Private",'Reference Lists'!$I$14,IF(tblIPD[[#This Row],[Ward type ]]="Private",'Reference Lists'!$I$15,IF(tblIPD[[#This Row],[Ward type ]]="ICU",'Reference Lists'!$I$17,IF(tblIPD[[#This Row],[Ward type ]]="CCU",'Reference Lists'!$I$16,""))))) -> 4000 | J6: =IF(tblIPD[[#This Row],[Ward type ]]="General",'Reference Lists'!$B$13,IF(tblIPD[[#This Row],[Ward type ]]="Semi-Private",'Reference Lists'!$B$14,IF(tblIPD[[#This Row],[Ward type ]]="Private",'Reference Lists'!$B$15,IF(tblIPD[[#This Row],[Ward type ]]="ICU",'Reference Lists'!$B$16,IF(tblIPD[[#This Row],[Ward type ]]="CCU",'Reference Lists'!$B$17,""))))) -> 2000 | K6: =IF(tblIPD[[#This Row],[Ward type ]]="General",'Reference Lists'!$E$4,IF(tblIPD[[#This Row],[Ward type ]]="Semi-Private",'Reference Lists'!$E$5,IF(tblIPD[[#This Row],[Ward type ]]="Private",'Reference Lists'!$E$6,IF(tblIPD[[#This Row],[Ward type ]]="ICU",'Reference Lists'!$B$16,IF(tblIPD[[#This Row],[Ward type ]]="CCU",'Reference Lists'!$B$17,""))))) -> 800 | L6: =IF(tblIPD[[#This Row],[Ward type ]]="General",'Reference Lists'!$E$13,IF(tblIPD[[#This Row],[Ward type ]]="Semi-Private",'Reference Lists'!$E$14,IF(tblIPD[[#This Row],[Ward type ]]="Private",'Reference Lists'!$E$15,IF(tblIPD[[#This Row],[Ward type ]]="ICU",'Reference Lists'!$E$16,IF(tblIPD[[#This Row],[Ward type ]]="CCU",'Reference Lists'!$E$17,""))))) -> 1200 | N6: =(tblIPD[[#This Row],[Other charges]]+tblIPD[[#This Row],[Doctor charges]]+tblIPD[[#This Row],[Nursing charges]]+tblIPD[[#This Row],[Room Charges]]+tblIPD[[#This Row],[Rate per day]])*tblIPD[[#This Row],[No. of days]] -> 64000 | O6: Paid | P6: Card | Q6: 46013 | R6: =tblIPD[[#This Row],[Total Amount]]*VLOOKUP(tblIPD[[#This Row],[Ward type ]],'Reference Lists'!$A$4:$B$8,2,FALSE) -> 4480 | S6: =tblIPD[[#This Row],[Total Amount]]-tblIPD[[#This Row],[Discount]] -> 59520
A7: INV.IPD-3 | B7: P-015 | C7: =_xlfn.XLOOKUP(tblIPD[[#This Row],[Patient id.]],Tbl.PatRec[Patient ID],Tbl.PatRec[Name],"",0) -> Name 15 | D7: ICU | E7: 10 | F7: 46006 | G7: 46020 | H7: =tblIPD[[#This Row],[Discharge date]]-tblIPD[[#This Row],[Admission date ]]+1 -> 15 | I7: =IF(tblIPD[[#This Row],[Ward type ]]="General",'Reference Lists'!$I$13,IF(tblIPD[[#This Row],[Ward type ]]="Semi-Private",'Reference Lists'!$I$14,IF(tblIPD[[#This Row],[Ward type ]]="Private",'Reference Lists'!$I$15,IF(tblIPD[[#This Row],[Ward type ]]="ICU",'Reference Lists'!$I$17,IF(tblIPD[[#This Row],[Ward type ]]="CCU",'Reference Lists'!$I$16,""))))) -> 15000 | J7: =IF(tblIPD[[#This Row],[Ward type ]]="General",'Reference Lists'!$B$13,IF(tblIPD[[#This Row],[Ward type ]]="Semi-Private",'Reference Lists'!$B$14,IF(tblIPD[[#This Row],[Ward type ]]="Private",'Reference Lists'!$B$15,IF(tblIPD[[#This Row],[Ward type ]]="ICU",'Reference Lists'!$B$16,IF(tblIPD[[#This Row],[Ward type ]]="CCU",'Reference Lists'!$B$17,""))))) -> 8000 | K7: =IF(tblIPD[[#This Row],[Ward type ]]="General",'Reference Lists'!$E$4,IF(tblIPD[[#This Row],[Ward type ]]="Semi-Private",'Reference Lists'!$E$5,IF(tblIPD[[#This Row],[Ward type ]]="Private",'Reference Lists'!$E$6,IF(tblIPD[[#This Row],[Ward type ]]="ICU",'Reference Lists'!$B$16,IF(tblIPD[[#This Row],[Ward type ]]="CCU",'Reference Lists'!$B$17,""))))) -> 8000 | L7: =IF(tblIPD[[#This Row],[Ward type ]]="General",'Reference Lists'!$E$13,IF(tblIPD[[#This Row],[Ward type ]]="Semi-Private",'Reference Lists'!$E$14,IF(tblIPD[[#This Row],[Ward type ]]="Private",'Reference Lists'!$E$15,IF(tblIPD[[#This Row],[Ward type ]]="ICU",'Reference Lists'!$E$16,IF(tblIPD[[#This Row],[Ward type ]]="CCU",'Reference Lists'!$E$17,""))))) -> 2500 | N7: =(tblIPD[[#This Row],[Other charges]]+tblIPD[[#This Row],[Doctor charges]]+tblIPD[[#This Row],[Nursing charges]]+tblIPD[[#This Row],[Room Charges]]+tblIPD[[#This Row],[Rate per day]])*tblIPD[[#This Row],[No. of days]] -> 502500 | O7: Unpaid | R7: =tblIPD[[#This Row],[Total Amount]]*VLOOKUP(tblIPD[[#This Row],[Ward type ]],'Reference Lists'!$A$4:$B$8,2,FALSE) -> 25125 | S7: =tblIPD[[#This Row],[Total Amount]]-tblIPD[[#This Row],[Discount]] -> 477375
A8: INV.IPD-4 | B8: P-009 | C8: =_xlfn.XLOOKUP(tblIPD[[#This Row],[Patient id.]],Tbl.PatRec[Patient ID],Tbl.PatRec[Name],"",0) -> Name 9 | D8: Private | E8: 1 | F8: 45993 | G8: 46006 | H8: =tblIPD[[#This Row],[Discharge date]]-tblIPD[[#This Row],[Admission date ]]+1 -> 14 | I8: =IF(tblIPD[[#This Row],[Ward type ]]="General",'Reference Lists'!$I$13,IF(tblIPD[[#This Row],[Ward type ]]="Semi-Private",'Reference Lists'!$I$14,IF(tblIPD[[#This Row],[Ward type ]]="Private",'Reference Lists'!$I$15,IF(tblIPD[[#This Row],[Ward type ]]="ICU",'Reference Lists'!$I$17,IF(tblIPD[[#This Row],[Ward type ]]="CCU",'Reference Lists'!$I$16,""))))) -> 8000 | J8: =IF(tblIPD[[#This Row],[Ward type ]]="General",'Reference Lists'!$B$13,IF(tblIPD[[#This Row],[Ward type ]]="Semi-Private",'Reference Lists'!$B$14,IF(tblIPD[[#This Row],[Ward type ]]="Private",'Reference Lists'!$B$15,IF(tblIPD[[#This Row],[Ward type ]]="ICU",'Reference Lists'!$B$16,IF(tblIPD[[#This Row],[Ward type ]]="CCU",'Reference Lists'!$B$17,""))))) -> 3000 | K8: =IF(tblIPD[[#This Row],[Ward type ]]="General",'Reference Lists'!$E$4,IF(tblIPD[[#This Row],[Ward type ]]="Semi-Private",'Reference Lists'!$E$5,IF(tblIPD[[#This Row],[Ward type ]]="Private",'Reference Lists'!$E$6,IF(tblIPD[[#This Row],[Ward type ]]="ICU",'Reference Lists'!$B$16,IF(tblIPD[[#This Row],[Ward type ]]="CCU",'Reference Lists'!$B$17,""))))) -> 1200 | L8: =IF(tblIPD[[#This Row],[Ward type ]]="General",'Reference Lists'!$E$13,IF(tblIPD[[#This Row],[Ward type ]]="Semi-Private",'Reference Lists'!$E$14,IF(tblIPD[[#This Row],[Ward type ]]="Private",'Reference Lists'!$E$15,IF(tblIPD[[#This Row],[Ward type ]]="ICU",'Reference Lists'!$E$16,IF(tblIPD[[#This Row],[Ward type ]]="CCU",'Reference Lists'!$E$17,""))))) -> 2000 | N8: =(tblIPD[[#This Row],[Other charges]]+tblIPD[[#This Row],[Doctor charges]]+tblIPD[[#This Row],[Nursing charges]]+tblIPD[[#This Row],[Room Charges]]+tblIPD[[#This Row],[Rate per day]])*tblIPD[[#This Row],[No. of days]] -> 198800 | O8: Unpaid | R8: =tblIPD[[#This Row],[Total Amount]]*VLOOKUP(tblIPD[[#This Row],[Ward type ]],'Reference Lists'!$A$4:$B$8,2,FALSE) -> 19880 | S8: =tblIPD[[#This Row],[Total Amount]]-tblIPD[[#This Row],[Discount]] -> 178920
A9: INV.IPD-5 | B9: P-004 | C9: =_xlfn.XLOOKUP(tblIPD[[#This Row],[Patient id.]],Tbl.PatRec[Patient ID],Tbl.PatRec[Name],"",0) -> Name 4 | D9: General | E9: 3 | F9: 46003 | G9: 46011 | H9: =tblIPD[[#This Row],[Discharge date]]-tblIPD[[#This Row],[Admission date ]]+1 -> 9 | I9: =IF(tblIPD[[#This Row],[Ward type ]]="General",'Reference Lists'!$I$13,IF(tblIPD[[#This Row],[Ward type ]]="Semi-Private",'Reference Lists'!$I$14,IF(tblIPD[[#This Row],[Ward type ]]="Private",'Reference Lists'!$I$15,IF(tblIPD[[#This Row],[Ward type ]]="ICU",'Reference Lists'!$I$17,IF(tblIPD[[#This Row],[Ward type ]]="CCU",'Reference Lists'!$I$16,""))))) -> 2000 | J9: =IF(tblIPD[[#This Row],[Ward type ]]="General",'Reference Lists'!$B$13,IF(tblIPD[[#This Row],[Ward type ]]="Semi-Private",'Reference Lists'!$B$14,IF(tblIPD[[#This Row],[Ward type ]]="Private",'Reference Lists'!$B$15,IF(tblIPD[[#This Row],[Ward type ]]="ICU",'Reference Lists'!$B$16,IF(tblIPD[[#This Row],[Ward type ]]="CCU",'Reference Lists'!$B$17,""))))) -> 700 | K9: =IF(tblIPD[[#This Row],[Ward type ]]="General",'Reference Lists'!$E$4,IF(tblIPD[[#This Row],[Ward type ]]="Semi-Private",'Reference Lists'!$E$5,IF(tblIPD[[#This Row],[Ward type ]]="Private",'Reference Lists'!$E$6,IF(tblIPD[[#This Row],[Ward type ]]="ICU",'Reference Lists'!$B$16,IF(tblIPD[[#This Row],[Ward type ]]="CCU",'Reference Lists'!$B$17,""))))) -> 500 | L9: =IF(tblIPD[[#This Row],[Ward type ]]="General",'Reference Lists'!$E$13,IF(tblIPD[[#This Row],[Ward type ]]="Semi-Private",'Reference Lists'!$E$14,IF(tblIPD[[#This Row],[Ward type ]]="Private",'Reference Lists'!$E$15,IF(tblIPD[[#This Row],[Ward type ]]="ICU",'Reference Lists'!$E$16,IF(tblIPD[[#This Row],[Ward type ]]="CCU",'Reference Lists'!$E$17,""))))) -> 500 | N9: =(tblIPD[[#This Row],[Other charges]]+tblIPD[[#This Row],[Doctor charges]]+tblIPD[[#This Row],[Nursing charges]]+tblIPD[[#This Row],[Room Charges]]+tblIPD[[#This Row],[Rate per day]])*tblIPD[[#This Row],[No. of days]] -> 33300 | O9: Paid | P9: Insurance | R9: =tblIPD[[#This Row],[Total Amount]]*VLOOKUP(tblIPD[[#This Row],[Ward type ]],'Reference Lists'!$A$4:$B$8,2,FALSE) -> 1665 | S9: =tblIPD[[#This Row],[Total Amount]]-tblIPD[[#This Row],[Discount]] -> 31635
A10: INV.IPD-6 | B10: P-007 | C10: =_xlfn.XLOOKUP(tblIPD[[#This Row],[Patient id.]],Tbl.PatRec[Patient ID],Tbl.PatRec[Name],"",0) -> Name 7 | D10: CCU | E10: 7 | F10: 45994 | G10: 46010 | H10: =tblIPD[[#This Row],[Discharge date]]-tblIPD[[#This Row],[Admission date ]]+1 -> 17 | I10: =IF(tblIPD[[#This Row],[Ward type ]]="General",'Reference Lists'!$I$13,IF(tblIPD[[#This Row],[Ward type ]]="Semi-Private",'Reference Lists'!$I$14,IF(tblIPD[[#This Row],[Ward type ]]="Private",'Reference Lists'!$I$15,IF(tblIPD[[#This Row],[Ward type ]]="ICU",'Reference Lists'!$I$17,IF(tblIPD[[#This Row],[Ward type ]]="CCU",'Reference Lists'!$I$16,""))))) -> 12000 | J10: =IF(tblIPD[[#This Row],[Ward type ]]="General",'Reference Lists'!$B$13,IF(tblIPD[[#This Row],[Ward type ]]="Semi-Private",'Reference Lists'!$B$14,IF(tblIPD[[#This Row],[Ward type ]]="Private",'Reference Lists'!$B$15,IF(tblIPD[[#This Row],[Ward type ]]="ICU",'Reference Lists'!$B$16,IF(tblIPD[[#This Row],[Ward type ]]="CCU",'Reference Lists'!$B$17,""))))) -> 6000 | K10: =IF(tblIPD[[#This Row],[Ward type ]]="General",'Reference Lists'!$E$4,IF(tblIPD[[#This Row],[Ward type ]]="Semi-Private",'Reference Lists'!$E$5,IF(tblIPD[[#This Row],[Ward type ]]="Private",'Reference Lists'!$E$6,IF(tblIPD[[#This Row],[Ward type ]]="ICU",'Reference Lists'!$B$16,IF(tblIPD[[#This Row],[Ward type ]]="CCU",'Reference Lists'!$B$17,""))))) -> 6000 | L10: =IF(tblIPD[[#This Row],[Ward type ]]="General",'Reference Lists'!$E$13,IF(tblIPD[[#This Row],[Ward type ]]="Semi-Private",'Reference Lists'!$E$14,IF(tblIPD[[#This Row],[Ward type ]]="Private",'Reference Lists'!$E$15,IF(tblIPD[[#This Row],[Ward type ]]="ICU",'Reference Lists'!$E$16,IF(tblIPD[[#This Row],[Ward type ]]="CCU",'Reference Lists'!$E$17,""))))) -> 2200 | N10: =(tblIPD[[#This Row],[Other charges]]+tblIPD[[#This Row],[Doctor charges]]+tblIPD[[#This Row],[Nursing charges]]+tblIPD[[#This Row],[Room Charges]]+tblIPD[[#This Row],[Rate per day]])*tblIPD[[#This Row],[No. of days]] -> 445400 | O10: Unpaid | R10: =tblIPD[[#This Row],[Total Amount]]*VLOOKUP(tblIPD[[#This Row],[Ward type ]],'Reference Lists'!$A$4:$B$8,2,FALSE) -> 35632 | S10: =tblIPD[[#This Row],[Total Amount]]-tblIPD[[#This Row],[Discount]] -> 409768
A11: INV.IPD-7 | B11: P-011 | C11: =_xlfn.XLOOKUP(tblIPD[[#This Row],[Patient id.]],Tbl.PatRec[Patient ID],Tbl.PatRec[Name],"",0) -> Name 11 | D11: Private | E11: 1 | F11: 45994 | G11: 46002 | H11: =tblIPD[[#This Row],[Discharge date]]-tblIPD[[#This Row],[Admission date ]]+1 -> 9 | I11: =IF(tblIPD[[#This Row],[Ward type ]]="General",'Reference Lists'!$I$13,IF(tblIPD[[#This Row],[Ward type ]]="Semi-Private",'Reference Lists'!$I$14,IF(tblIPD[[#This Row],[Ward type ]]="Private",'Reference Lists'!$I$15,IF(tblIPD[[#This Row],[Ward type ]]="ICU",'Reference Lists'!$I$17,IF(tblIPD[[#This Row],[Ward type ]]="CCU",'Reference Lists'!$I$16,""))))) -> 8000 | J11: =IF(tblIPD[[#This Row],[Ward type ]]="General",'Reference Lists'!$B$13,IF(tblIPD[[#This Row],[Ward type ]]="Semi-Private",'Reference Lists'!$B$14,IF(tblIPD[[#This Row],[Ward type ]]="Private",'Reference Lists'!$B$15,IF(tblIPD[[#This Row],[Ward type ]]="ICU",'Reference Lists'!$B$16,IF(tblIPD[[#This Row],[Ward type ]]="CCU",'Reference Lists'!$B$17,""))))) -> 3000 | K11: =IF(tblIPD[[#This Row],[Ward type ]]="General",'Reference Lists'!$E$4,IF(tblIPD[[#This Row],[Ward type ]]="Semi-Private",'Reference Lists'!$E$5,IF(tblIPD[[#This Row],[Ward type ]]="Private",'Reference Lists'!$E$6,IF(tblIPD[[#This Row],[Ward type ]]="ICU",'Reference Lists'!$B$16,IF(tblIPD[[#This Row],[Ward type ]]="CCU",'Reference Lists'!$B$17,""))))) -> 1200 | L11: =IF(tblIPD[[#This Row],[Ward type ]]="General",'Reference Lists'!$E$13,IF(tblIPD[[#This Row],[Ward type ]]="Semi-Private",'Reference Lists'!$E$14,IF(tblIPD[[#This Row],[Ward type ]]="Private",'Reference Lists'!$E$15,IF(tblIPD[[#This Row],[Ward type ]]="ICU",'Reference Lists'!$E$16,IF(tblIPD[[#This Row],[Ward type ]]="CCU",'Reference Lists'!$E$17,""))))) -> 2000 | N11: =(tblIPD[[#This Row],[Other charges]]+tblIPD[[#This Row],[Doctor charges]]+tblIPD[[#This Row],[Nursing charges]]+tblIPD[[#This Row],[Room Charges]]+tblIPD[[#This Row],[Rate per day]])*tblIPD[[#This Row],[No. of days]] -> 127800 | O11: Unpaid | R11: =tblIPD[[#This Row],[Total Amount]]*VLOOKUP(tblIPD[[#This Row],[Ward type ]],'Reference Lists'!$A$4:$B$8,2,FALSE) -> 12780 | S11: =tblIPD[[#This Row],[Total Amount]]-tblIPD[[#This Row],[Discount]] -> 115020
A12: INV.IPD-8 | B12: P-017 | C12: =_xlfn.XLOOKUP(tblIPD[[#This Row],[Patient id.]],Tbl.PatRec[Patient ID],Tbl.PatRec[Name],"",0) -> Name 17 | D12: General | E12: 2 | F12: 46008 | G12: 46013 | H12: =tblIPD[[#This Row],[Discharge date]]-tblIPD[[#This Row],[Admission date ]]+1 -> 6 | I12: =IF(tblIPD[[#This Row],[Ward type ]]="General",'Reference Lists'!$I$13,IF(tblIPD[[#This Row],[Ward type ]]="Semi-Private",'Reference Lists'!$I$14,IF(tblIPD[[#This Row],[Ward type ]]="Private",'Reference Lists'!$I$15,IF(tblIPD[[#This Row],[Ward type ]]="ICU",'Reference Lists'!$I$17,IF(tblIPD[[#This Row],[Ward type ]]="CCU",'Reference Lists'!$I$16,""))))) -> 2000 | J12: =IF(tblIPD[[#This Row],[Ward type ]]="General",'Reference Lists'!$B$13,IF(tblIPD[[#This Row],[Ward type ]]="Semi-Private",'Reference Lists'!$B$14,IF(tblIPD[[#This Row],[Ward type ]]="Private",'Reference Lists'!$B$15,IF(tblIPD[[#This Row],[Ward type ]]="ICU",'Reference Lists'!$B$16,IF(tblIPD[[#This Row],[Ward type ]]="CCU",'Reference Lists'!$B$17,""))))) -> 700 | K12: =IF(tblIPD[[#This Row],[Ward type ]]="General",'Reference Lists'!$E$4,IF(tblIPD[[#This Row],[Ward type ]]="Semi-Private",'Reference Lists'!$E$5,IF(tblIPD[[#This Row],[Ward type ]]="Private",'Reference Lists'!$E$6,IF(tblIPD[[#This Row],[Ward type ]]="ICU",'Reference Lists'!$B$16,IF(tblIPD[[#This Row],[Ward type ]]="CCU",'Reference Lists'!$B$17,""))))) -> 500 | L12: =IF(tblIPD[[#This Row],[Ward type ]]="General",'Reference Lists'!$E$13,IF(tblIPD[[#This Row],[Ward type ]]="Semi-Private",'Reference Lists'!$E$14,IF(tblIPD[[#This Row],[Ward type ]]="Private",'Reference Lists'!$E$15,IF(tblIPD[[#This Row],[Ward type ]]="ICU",'Reference Lists'!$E$16,IF(tblIPD[[#This Row],[Ward type ]]="CCU",'Reference Lists'!$E$17,""))))) -> 500 | N12: =(tblIPD[[#This Row],[Other charges]]+tblIPD[[#This Row],[Doctor charges]]+tblIPD[[#This Row],[Nursing charges]]+tblIPD[[#This Row],[Room Charges]]+tblIPD[[#This Row],[Rate per day]])*tblIPD[[#This Row],[No. of days]] -> 22200 | O12: Paid | P12: Card | Q12: 46013 | R12: =tblIPD[[#This Row],[Total Amount]]*VLOOKUP(tblIPD[[#This Row],[Ward type ]],'Reference Lists'!$A$4:$B$8,2,FALSE) -> 1110 | S12: =tblIPD[[#This Row],[Total Amount]]-tblIPD[[#This Row],[Discount]] -> 21090
A13: INV.IPD-9 | B13: P-013 | C13: =_xlfn.XLOOKUP(tblIPD[[#This Row],[Patient id.]],Tbl.PatRec[Patient ID],Tbl.PatRec[Name],"",0) -> Name 13 | D13: General | E13: 1 | F13: 45992 | G13: 45999 | H13: =tblIPD[[#This Row],[Discharge date]]-tblIPD[[#This Row],[Admission date ]]+1 -> 8 | I13: =IF(tblIPD[[#This Row],[Ward type ]]="General",'Reference Lists'!$I$13,IF(tblIPD[[#This Row],[Ward type ]]="Semi-Private",'Reference Lists'!$I$14,IF(tblIPD[[#This Row],[Ward type ]]="Private",'Reference Lists'!$I$15,IF(tblIPD[[#This Row],[Ward type ]]="ICU",'Reference Lists'!$I$17,IF(tblIPD[[#This Row],[Ward type ]]="CCU",'Reference Lists'!$I$16,""))))) -> 2000 | J13: =IF(tblIPD[[#This Row],[Ward type ]]="General",'Reference Lists'!$B$13,IF(tblIPD[[#This Row],[Ward type ]]="Semi-Private",'Reference Lists'!$B$14,IF(tblIPD[[#This Row],[Ward type ]]="Private",'Reference Lists'!$B$15,IF(tblIPD[[#This Row],[Ward type ]]="ICU",'Reference Lists'!$B$16,IF(tblIPD[[#This Row],[Ward type ]]="CCU",'Reference Lists'!$B$17,""))))) -> 700 | K13: =IF(tblIPD[[#This Row],[Ward type ]]="General",'Reference Lists'!$E$4,IF(tblIPD[[#This Row],[Ward type ]]="Semi-Private",'Reference Lists'!$E$5,IF(tblIPD[[#This Row],[Ward type ]]="Private",'Reference Lists'!$E$6,IF(tblIPD[[#This Row],[Ward type ]]="ICU",'Reference Lists'!$B$16,IF(tblIPD[[#This Row],[Ward type ]]="CCU",'Reference Lists'!$B$17,""))))) -> 500 | L13: =IF(tblIPD[[#This Row],[Ward type ]]="General",'Reference Lists'!$E$13,IF(tblIPD[[#This Row],[Ward type ]]="Semi-Private",'Reference Lists'!$E$14,IF(tblIPD[[#This Row],[Ward type ]]="Private",'Reference Lists'!$E$15,IF(tblIPD[[#This Row],[Ward type ]]="ICU",'Reference Lists'!$E$16,IF(tblIPD[[#This Row],[Ward type ]]="CCU",'Reference Lists'!$E$17,""))))) -> 500 | N13: =(tblIPD[[#This Row],[Other charges]]+tblIPD[[#This Row],[Doctor charges]]+tblIPD[[#This Row],[Nursing charges]]+tblIPD[[#This Row],[Room Charges]]+tblIPD[[#This Row],[Rate per day]])*tblIPD[[#This Row],[No. of days]] -> 29600 | O13: Paid | P13: Cash | Q13: 45999 | R13: =tblIPD[[#This Row],[Total Amount]]*VLOOKUP(tblIPD[[#This Row],[Ward type ]],'Reference Lists'!$A$4:$B$8,2,FALSE) -> 1480 | S13: =tblIPD[[#This Row],[Total Amount]]-tblIPD[[#This Row],[Discount]] -> 28120
A14: INV.IPD-10 | B14: P-019 | C14: =_xlfn.XLOOKUP(tblIPD[[#This Row],[Patient id.]],Tbl.PatRec[Patient ID],Tbl.PatRec[Name],"",0) -> Name 19 | D14: Semi-Private | E14: 1 | F14: 45997 | G14: 46004 | H14: =tblIPD[[#This Row],[Discharge date]]-tblIPD[[#This Row],[Admission date ]]+1 -> 8 | I14: =IF(tblIPD[[#This Row],[Ward type ]]="General",'Reference Lists'!$I$13,IF(tblIPD[[#This Row],[Ward type ]]="Semi-Private",'Reference Lists'!$I$14,IF(tblIPD[[#This Row],[Ward type ]]="Private",'Reference Lists'!$I$15,IF(tblIPD[[#This Row],[Ward type ]]="ICU",'Reference Lists'!$I$17,IF(tblIPD[[#This Row],[Ward type ]]="CCU",'Reference Lists'!$I$16,""))))) -> 4000 | J14: =IF(tblIPD[[#This Row],[Ward type ]]="General",'Reference Lists'!$B$13,IF(tblIPD[[#This Row],[Ward type ]]="Semi-Private",'Reference Lists'!$B$14,IF(tblIPD[[#This Row],[Ward type ]]="Private",'Reference Lists'!$B$15,IF(tblIPD[[#This Row],[Ward type ]]="ICU",'Reference Lists'!$B$16,IF(tblIPD[[#This Row],[Ward type ]]="CCU",'Reference Lists'!$B$17,""))))) -> 2000 | K14: =IF(tblIPD[[#This Row],[Ward type ]]="General",'Reference Lists'!$E$4,IF(tblIPD[[#This Row],[Ward type ]]="Semi-Private",'Reference Lists'!$E$5,IF(tblIPD[[#This Row],[Ward type ]]="Private",'Reference Lists'!$E$6,IF(tblIPD[[#This Row],[Ward type ]]="ICU",'Reference Lists'!$B$16,IF(tblIPD[[#This Row],[Ward type ]]="CCU",'Reference Lists'!$B$17,""))))) -> 800 | L14: =IF(tblIPD[[#This Row],[Ward type ]]="General",'Reference Lists'!$E$13,IF(tblIPD[[#This Row],[Ward type ]]="Semi-Private",'Reference Lists'!$E$14,IF(tblIPD[[#This Row],[Ward type ]]="Private",'Reference Lists'!$E$15,IF(tblIPD[[#This Row],[Ward type ]]="ICU",'Reference Lists'!$E$16,IF(tblIPD[[#This Row],[Ward type ]]="CCU",'Reference Lists'!$E$17,""))))) -> 1200 | N14: =(tblIPD[[#This Row],[Other charges]]+tblIPD[[#This Row],[Doctor charges]]+tblIPD[[#This Row],[Nursing charges]]+tblIPD[[#This Row],[Room Charges]]+tblIPD[[#This Row],[Rate per day]])*tblIPD[[#This Row],[No. of days]] -> 64000 | O14: Paid | P14: Insurance | Q14: 46004 | R14: =tblIPD[[#This Row],[Total Amount]]*VLOOKUP(tblIPD[[#This Row],[Ward type ]],'Reference Lists'!$A$4:$B$8,2,FALSE) -> 4480 | S14: =tblIPD[[#This Row],[Total Amount]]-tblIPD[[#This Row],[Discount]] -> 59520
A15: INV.IPD-11 | B15: P-008 | C15: =_xlfn.XLOOKUP(tblIPD[[#This Row],[Patient id.]],Tbl.PatRec[Patient ID],Tbl.PatRec[Name],"",0) -> Name 8 | H15: =tblIPD[[#This Row],[Discharge date]]-tblIPD[[#This Row],[Admission date ]]+1 -> 1 | I15: =IF(tblIPD[[#This Row],[Ward type ]]="General",'Reference Lists'!$I$13,IF(tblIPD[[#This Row],[Ward type ]]="Semi-Private",'Reference Lists'!$I$14,IF(tblIPD[[#This Row],[Ward type ]]="Private",'Reference Lists'!$I$15,IF(tblIPD[[#This Row],[Ward type ]]="ICU",'Reference Lists'!$I$17,IF(tblIPD[[#This Row],[Ward type ]]="CCU",'Reference Lists'!$I$16,""))))) | J15: =IF(tblIPD[[#This Row],[Ward type ]]="General",'Reference Lists'!$B$13,IF(tblIPD[[#This Row],[Ward type ]]="Semi-Private",'Reference Lists'!$B$14,IF(tblIPD[[#This Row],[Ward type ]]="Private",'Reference Lists'!$B$15,IF(tblIPD[[#This Row],[Ward type ]]="ICU",'Reference Lists'!$B$16,IF(tblIPD[[#This Row],[Ward type ]]="CCU",'Reference Lists'!$B$17,""))))) | K15: =IF(tblIPD[[#This Row],[Ward type ]]="General",'Reference Lists'!$E$4,IF(tblIPD[[#This Row],[Ward type ]]="Semi-Private",'Reference Lists'!$E$5,IF(tblIPD[[#This Row],[Ward type ]]="Private",'Reference Lists'!$E$6,IF(tblIPD[[#This Row],[Ward type ]]="ICU",'Reference Lists'!$B$16,IF(tblIPD[[#This Row],[Ward type ]]="CCU",'Reference Lists'!$B$17,""))))) | L15: =IF(tblIPD[[#This Row],[Ward type ]]="General",'Reference Lists'!$E$13,IF(tblIPD[[#This Row],[Ward type ]]="Semi-Private",'Reference Lists'!$E$14,IF(tblIPD[[#This Row],[Ward type ]]="Private",'Reference Lists'!$E$15,IF(tblIPD[[#This Row],[Ward type ]]="ICU",'Reference Lists'!$E$16,IF(tblIPD[[#This Row],[Ward type ]]="CCU",'Reference Lists'!$E$17,""))))) | N15: =(tblIPD[[#This Row],[Other charges]]+tblIPD[[#This Row],[Doctor charges]]+tblIPD[[#This Row],[Nursing charges]]+tblIPD[[#This Row],[Room Charges]]+tblIPD[[#This Row],[Rate per day]])*tblIPD[[#This Row],[No. of days]] -> #VALUE! | R15: =tblIPD[[#This Row],[Total Amount]]*VLOOKUP(tblIPD[[#This Row],[Ward type ]],'Reference Lists'!$A$4:$B$8,2,FALSE) -> #VALUE! | S15: =tblIPD[[#This Row],[Total Amount]]-tblIPD[[#This Row],[Discount]] -> #VALUE!
B16: P-014 | C16: =_xlfn.XLOOKUP(tblIPD[[#This Row],[Patient id.]],Tbl.PatRec[Patient ID],Tbl.PatRec[Name],"",0) -> Name 14 | H16: =tblIPD[[#This Row],[Discharge date]]-tblIPD[[#This Row],[Admission date ]]+1 -> 1 | I16: =IF(tblIPD[[#This Row],[Ward type ]]="General",'Reference Lists'!$I$13,IF(tblIPD[[#This Row],[Ward type ]]="Semi-Private",'Reference Lists'!$I$14,IF(tblIPD[[#This Row],[Ward type ]]="Private",'Reference Lists'!$I$15,IF(tblIPD[[#This Row],[Ward type ]]="ICU",'Reference Lists'!$I$17,IF(tblIPD[[#This Row],[Ward type ]]="CCU",'Reference Lists'!$I$16,""))))) | J16: =IF(tblIPD[[#This Row],[Ward type ]]="General",'Reference Lists'!$B$13,IF(tblIPD[[#This Row],[Ward type ]]="Semi-Private",'Reference Lists'!$B$14,IF(tblIPD[[#This Row],[Ward type ]]="Private",'Reference Lists'!$B$15,IF(tblIPD[[#This Row],[Ward type ]]="ICU",'Reference Lists'!$B$16,IF(tblIPD[[#This Row],[Ward type ]]="CCU",'Reference Lists'!$B$17,""))))) | K16: =IF(tblIPD[[#This Row],[Ward type ]]="General",'Reference Lists'!$E$4,IF(tblIPD[[#This Row],[Ward type ]]="Semi-Private",'Reference Lists'!$E$5,IF(tblIPD[[#This Row],[Ward type ]]="Private",'Reference Lists'!$E$6,IF(tblIPD[[#This Row],[Ward type ]]="ICU",'Reference Lists'!$B$16,IF(tblIPD[[#This Row],[Ward type ]]="CCU",'Reference Lists'!$B$17,""))))) | L16: =IF(tblIPD[[#This Row],[Ward type ]]="General",'Reference Lists'!$E$13,IF(tblIPD[[#This Row],[Ward type ]]="Semi-Private",'Reference Lists'!$E$14,IF(tblIPD[[#This Row],[Ward type ]]="Private",'Reference Lists'!$E$15,IF(tblIPD[[#This Row],[Ward type ]]="ICU",'Reference Lists'!$E$16,IF(tblIPD[[#This Row],[Ward type ]]="CCU",'Reference Lists'!$E$17,""))))) | N16: =(tblIPD[[#This Row],[Other charges]]+tblIPD[[#This Row],[Doctor charges]]+tblIPD[[#This Row],[Nursing charges]]+tblIPD[[#This Row],[Room Charges]]+tblIPD[[#This Row],[Rate per day]])*tblIPD[[#This Row],[No. of days]] -> #VALUE! | R16: =tblIPD[[#This Row],[Total Amount]]*VLOOKUP(tblIPD[[#This Row],[Ward type ]],'Reference Lists'!$A$4:$B$8,2,FALSE) -> #VALUE! | S16: =tblIPD[[#This Row],[Total Amount]]-tblIPD[[#This Row],[Discount]] -> #VALUE!

Sheet Reference Lists
A3: Discounts for IPD Billing | D3: Nursing Charges | H3: Ward rates per day | K3: Blood Group List
A4: General | B4: 0.05 | D4: General | E4: 500 | H4: General | I4: 2000 | K4: A+
A5: Semi-Private | B5: 0.07 | D5: Semi-Private | E5: 800 | H5: Semi-Private | I5: 4000 | K5: A-
A6: Private | B6: 0.1 | D6: Private | E6: 1200 | H6: Private | I6: 8000 | K6: A
A7: ICU | B7: 0.05 | D7: ICU | E7: 2500 | H7: CCU | I7: 12000 | K7: B+
A8: CCU | B8: 0.08 | D8: CCU | E8: 2000 | H8: ICU | I8: 15000 | K8: B-
K9: B
K10: AB+
K11: AB-
A12: Room Charges | D12: Doctor Charges | H12: Ward rates per day | K12: O+
A13: General | B13: 700 | D13: General | E13: 500 | H13: General | I13: 2000 | K13: O-
A14: Semi-Private | B14: 2000 | D14: Semi-Private | E14: 1200 | H14: Semi-Private | I14: 4000
A15: Private | B15: 3000 | D15: Private | E15: 2000 | H15: Private | I15: 8000
A16: ICU | B16: 8000 | D16: ICU | E16: 2500 | H16: CCU | I16: 12000
A17: CCU | B17: 6000 | D17: CCU | E17: 2200 | H17: ICU | I17: 15000
A24: Procedure Name | B24: Sample Rate (PKR) | C24: Category | D24: Discounts | F24: Procedure Name
A25: Consultation (General) | B25: 1000 | C25: Consultation | D25: 0.05 | F25: Consultation (General)
A26: Consultation (Specialist/Professor) | B26: 2500 | C26: Consultation | D26: 0.08 | F26: Consultation (Specialist/Professor)
A27: Emergency Visit Fee | B27: 1000 | C27: Emergency | D27: 0.05 | F27: Emergency Visit
A28: Dressing (Minor) | B28: 500 | C28: Nursing Care | D28: 0 | F28: Dressing (Minor)
A29: Dressing (Major) | B29: 1500 | C29: Nursing Care | D29: 0.06 | F29: Dressing (Major)
A30: Stitch Removal | B30: 1000 | C30: Minor Procedure | D30: 0.05 | F30: Stitch Removal
A31: Injection Fee (IM/IV) | B31: 200 | C31: Nursing Care | D31: 0 | F31: Injection (IM/IV)
A32: Nebulization (Per session) | B32: 400 | C32: Respiratory | D32: 0 | F32: Nebulization
A33: ECG | B33: 800 | C33: Cardiac | F33: ECG
A34: Ultrasound | B34: 2500 | C34: Radiology | D34: 0.08 | F34: Ultrasound
A35: X-Ray | B35: 1200 | C35: Radiology | D35: 0.06 | F35: X-Ray
A36: Blood Sugar | B36: 150 | C36: Lab | D36: 0 | F36: Blood Sugar
A37: C-Section | B37: 35000 | C37: Surgery (IPD/OPD Stay) | D37: 0.15 | F37: C-Section
A38: Circumcision | B38: 5000 | C38: Minor Surgery | D38: 0.1 | F38: Circumcision
